cronparse.py
cronparse-0.3.0.dist-info/WHEEL
cronparse-0.3.0.dist-info/METADATA
cronparse-0.3.0.dist-info/RECORD
