Metadata-Version: 2.1
Name: cronparse
Version: 0.3.0
Summary: A small tool for processing crontab syntax
License: MIT
Author: Curtis Maloney
Author-email: curtis@tinbrain.net
Requires-Python: >=3.6,<4.0
Classifier: License :: OSI Approved :: MIT License
Classifier: Programming Language :: Python :: 3
Classifier: Programming Language :: Python :: 3.6
Classifier: Programming Language :: Python :: 3.7
Classifier: Programming Language :: Python :: 3.8
